{
	"name": "blobstoragetosql",
	"properties": {
		"activities": [
			{
				"name": "Copy data1",
				"type": "Copy",
				"dependsOn": [],
				"policy": {
					"timeout": "0.12:00:00",
					"retry": 0,
					"retryIntervalInSeconds": 30,
					"secureOutput": false,
					"secureInput": false
				},
				"userProperties": [],
				"typeProperties": {
					"source": {
						"type": "DelimitedTextSource",
						"storeSettings": {
							"type": "AzureBlobStorageReadSettings",
							"recursive": true,
							"wildcardFileName": "*csv",
							"enablePartitionDiscovery": false
						},
						"formatSettings": {
							"type": "DelimitedTextReadSettings"
						}
					},
					"sink": {
						"type": "AzureSqlSink",
						"writeBehavior": "insert",
						"sqlWriterUseTableLock": false
					},
					"enableStaging": false,
					"translator": {
						"type": "TabularTranslator",
						"mappings": [
							{
								"source": {
									"type": "String",
									"ordinal": 1
								},
								"sink": {
									"name": "FirstName",
									"type": "String",
									"physicalType": "varchar"
								}
							},
							{
								"source": {
									"type": "String",
									"ordinal": 2
								},
								"sink": {
									"name": "LastName",
									"type": "String",
									"physicalType": "varchar"
								}
							},
							{
								"source": {
									"type": "String",
									"ordinal": 3
								},
								"sink": {
									"name": "Email",
									"type": "String",
									"physicalType": "varchar"
								}
							},
							{
								"source": {
									"type": "String",
									"ordinal": 4
								},
								"sink": {
									"name": "Address",
									"type": "String",
									"physicalType": "varchar"
								}
							},
							{
								"source": {
									"type": "String",
									"ordinal": 5
								},
								"sink": {
									"name": "City",
									"type": "String",
									"physicalType": "varchar"
								}
							},
							{
								"source": {
									"type": "String",
									"ordinal": 6
								},
								"sink": {
									"name": "DOB",
									"type": "String",
									"physicalType": "varchar"
								}
							}
						],
						"typeConversion": true,
						"typeConversionSettings": {
							"allowDataTruncation": true,
							"treatBooleanAsNumber": false
						}
					}
				},
				"inputs": [
					{
						"referenceName": "DelimitedText1",
						"type": "DatasetReference"
					}
				],
				"outputs": [
					{
						"referenceName": "AzureSqlTable6",
						"type": "DatasetReference",
						"parameters": {
							"SchemaName": "loga",
							"TableName": "Employee"
						}
					}
				]
			}
		],
		"annotations": [],
		"lastPublishTime": "2024-04-01T11:14:48Z"
	},
	"type": "Microsoft.DataFactory/factories/pipelines"
}